odoo/addons/repair_follow_lot_location/README.rst
odoo/addons/repair_follow_lot_location/__init__.py
odoo/addons/repair_follow_lot_location/__manifest__.py
odoo/addons/repair_follow_lot_location/i18n/it.po
odoo/addons/repair_follow_lot_location/i18n/repair_follow_lot_location.pot
odoo/addons/repair_follow_lot_location/models/__init__.py
odoo/addons/repair_follow_lot_location/models/repair_order.py
odoo/addons/repair_follow_lot_location/models/stock_move.py
odoo/addons/repair_follow_lot_location/readme/CONTRIBUTORS.md
odoo/addons/repair_follow_lot_location/readme/DESCRIPTION.md
odoo/addons/repair_follow_lot_location/readme/USAGE.md
odoo/addons/repair_follow_lot_location/static/description/icon.png
odoo/addons/repair_follow_lot_location/static/description/index.html
odoo/addons/repair_follow_lot_location/tests/__init__.py
odoo/addons/repair_follow_lot_location/tests/test_repair_follow_lot_location.py
odoo/addons/repair_follow_lot_location/views/repair_order_views.xml
odoo_addon_repair_follow_lot_location-16.0.1.0.0.2.dist-info/METADATA
odoo_addon_repair_follow_lot_location-16.0.1.0.0.2.dist-info/WHEEL
odoo_addon_repair_follow_lot_location-16.0.1.0.0.2.dist-info/top_level.txt
odoo_addon_repair_follow_lot_location-16.0.1.0.0.2.dist-info/RECORD
